skrl/__init__.py
skrl/agents/__init__.py
skrl/agents/jax/__init__.py
skrl/agents/jax/base.py
skrl/agents/jax/a2c/__init__.py
skrl/agents/jax/a2c/a2c.py
skrl/agents/jax/cem/__init__.py
skrl/agents/jax/cem/cem.py
skrl/agents/jax/ddpg/__init__.py
skrl/agents/jax/ddpg/ddpg.py
skrl/agents/jax/dqn/__init__.py
skrl/agents/jax/dqn/ddqn.py
skrl/agents/jax/dqn/dqn.py
skrl/agents/jax/ppo/__init__.py
skrl/agents/jax/ppo/ppo.py
skrl/agents/jax/rpo/__init__.py
skrl/agents/jax/rpo/rpo.py
skrl/agents/jax/sac/__init__.py
skrl/agents/jax/sac/sac.py
skrl/agents/jax/td3/__init__.py
skrl/agents/jax/td3/td3.py
skrl/agents/torch/__init__.py
skrl/agents/torch/base.py
skrl/agents/torch/a2c/__init__.py
skrl/agents/torch/a2c/a2c.py
skrl/agents/torch/a2c/a2c_rnn.py
skrl/agents/torch/amp/__init__.py
skrl/agents/torch/amp/amp.py
skrl/agents/torch/cem/__init__.py
skrl/agents/torch/cem/cem.py
skrl/agents/torch/ddpg/__init__.py
skrl/agents/torch/ddpg/ddpg.py
skrl/agents/torch/ddpg/ddpg_rnn.py
skrl/agents/torch/dqn/__init__.py
skrl/agents/torch/dqn/ddqn.py
skrl/agents/torch/dqn/dqn.py
skrl/agents/torch/ppo/__init__.py
skrl/agents/torch/ppo/ppo.py
skrl/agents/torch/ppo/ppo_rnn.py
skrl/agents/torch/q_learning/__init__.py
skrl/agents/torch/q_learning/q_learning.py
skrl/agents/torch/rpo/__init__.py
skrl/agents/torch/rpo/rpo.py
skrl/agents/torch/rpo/rpo_rnn.py
skrl/agents/torch/sac/__init__.py
skrl/agents/torch/sac/sac.py
skrl/agents/torch/sac/sac_rnn.py
skrl/agents/torch/sarsa/__init__.py
skrl/agents/torch/sarsa/sarsa.py
skrl/agents/torch/td3/__init__.py
skrl/agents/torch/td3/td3.py
skrl/agents/torch/td3/td3_rnn.py
skrl/agents/torch/trpo/__init__.py
skrl/agents/torch/trpo/trpo.py
skrl/agents/torch/trpo/trpo_rnn.py
skrl/envs/__init__.py
skrl/envs/jax.py
skrl/envs/torch.py
skrl/envs/loaders/__init__.py
skrl/envs/loaders/jax/__init__.py
skrl/envs/loaders/jax/bidexhands_envs.py
skrl/envs/loaders/jax/isaacgym_envs.py
skrl/envs/loaders/jax/isaaclab_envs.py
skrl/envs/loaders/jax/omniverse_isaacgym_envs.py
skrl-1.4.2.dist-info/LICENSE
skrl-1.4.2.dist-info/METADATA
skrl-1.4.2.dist-info/WHEEL
skrl-1.4.2.dist-info/top_level.txt
skrl-1.4.2.dist-info/RECORD
