Metadata-Version: 2.2
Name: skrl
Version: 1.4.2
Summary: Modular and flexible library for reinforcement learning on PyTorch and JAX
Author: Toni-SM
Maintainer: Toni-SM
License: MIT License
Project-URL: Homepage, https://github.com/Toni-SM/skrl
Project-URL: Documentation, https://skrl.readthedocs.io
Project-URL: Discussions, https://github.com/Toni-SM/skrl/discussions
Project-URL: Bug Reports, https://github.com/Toni-SM/skrl/issues
Project-URL: Say Thanks!, https://github.com/Toni-SM
Project-URL: Source, https://github.com/Toni-SM/skrl
Keywords: reinforcement-learning,machine-learning,reinforcement,machine,learning,rl
Classifier: License :: OSI Approved :: MIT License
Classifier: Intended Audience :: Science/Research
Classifier: Topic :: Scientific/Engineering
Classifier: Topic :: Scientific/Engineering :: Artificial Intelligence
Classifier: Programming Language :: Python :: 3
Classifier: Operating System :: OS Independent
Requires-Python: >=3.6
License-File: LICENSE
Requires-Dist: gymnasium
Requires-Dist: packaging
Requires-Dist: tensorboard
Requires-Dist: tqdm
Provides-Extra: torch
Requires-Dist: torch>=1.10; extra == "torch"
Provides-Extra: jax
Requires-Dist: jax>=0.4.3; extra == "jax"
Requires-Dist: jaxlib>=0.4.3; extra == "jax"
Requires-Dist: flax; extra == "jax"
Requires-Dist: optax; extra == "jax"
Provides-Extra: all
Requires-Dist: torch>=1.9; extra == "all"
Requires-Dist: jax>=0.4.3; extra == "all"
Requires-Dist: jaxlib>=0.4.3; extra == "all"
Requires-Dist: flax; extra == "all"
Requires-Dist: optax; extra == "all"
Provides-Extra: tests
Requires-Dist: pytest; extra == "tests"
Requires-Dist: hypothesis; extra == "tests"
